mazenv/__init__.py
mazenv/_util.py
mazenv/env.py
mazenv/generate.py
mazenv/maze.py
mazenv/test_env.py
mazenv/test_generate.py
mazenv/test_maze.py
mazenv-0.4.2.dist-info/METADATA
mazenv-0.4.2.dist-info/RECORD
mazenv-0.4.2.dist-info/WHEEL
mazenv-0.4.2.dist-info/top_level.txt
