Metadata-Version: 2.1
Name: mazenv
Version: 0.4.2
Summary: Maze environments for Reinforcement Learning
Home-page: https://github.com/unixpickle/mazenv-py
Author: Alex Nichol
Author-email: unixpickle@gmail.com
License: BSD
Keywords: ai reinforcement learning
Platform: UNKNOWN
Classifier: Development Status :: 4 - Beta
Classifier: Intended Audience :: Developers
Classifier: License :: OSI Approved :: BSD License
Classifier: Programming Language :: Python :: 3.5
Classifier: Programming Language :: Python :: 3.6
Requires-Dist: numpy (<2.0.0,>=1.0.0)
Requires-Dist: gym (<0.11.0,>=0.10.0)
